spatious/__init__.py
spatious/distance.py
spatious/distance_numerics.c
spatious/distance_numerics.pyx
spatious/distance_numerics.so
spatious/geom.py
spatious/geom_numerics.c
spatious/geom_numerics.pyx
spatious/geom_numerics.so
spatious/rotation.py
spatious/vector.py
spatious-0.1.2.dist-info/DESCRIPTION.rst
spatious-0.1.2.dist-info/METADATA
spatious-0.1.2.dist-info/metadata.json
spatious-0.1.2.dist-info/pbr.json
spatious-0.1.2.dist-info/RECORD
spatious-0.1.2.dist-info/top_level.txt
spatious-0.1.2.dist-info/WHEEL
